deeprep-1.8.0.dist-info/licenses/LICENSE.txt
dprep/__init__.py
dprep/dpdispatcher_tools.py
dprep/dptb_dpdispatcher.py
dprep/get_pp_orb_info.py
dprep/post_analysis_tools.py
deeprep-1.8.0.dist-info/METADATA
deeprep-1.8.0.dist-info/WHEEL
deeprep-1.8.0.dist-info/top_level.txt
deeprep-1.8.0.dist-info/RECORD
