Metadata-Version: 2.4
Name: deeprep
Version: 1.8.0
Summary: DPDispatcher REciPe for the Dataset PREParation of DeepTB.
Home-page: https://github.com/pyscaffold/pyscaffold/
Author: Franklalalala
Author-email: Liu Mingkang <1660810667@qq.com>
License: The MIT License (MIT)
Project-URL: Homepage, https://github.com/DeePTB-Lab/dprep
Project-URL: Bug Tracker, https://github.com/DeePTB-Lab/dprep/issues
Platform: any
Classifier: Programming Language :: Python :: 3
Classifier: License :: OSI Approved :: MIT License
Classifier: Intended Audience :: Science/Research
Requires-Python: >=3.8
License-File: LICENSE.txt
Requires-Dist: ase
Requires-Dist: dpdispatcher
Requires-Dist: pandas
Requires-Dist: numpy
Requires-Dist: matplotlib
Requires-Dist: reportlab
Requires-Dist: svglib
Requires-Dist: scipy
Provides-Extra: dev
Requires-Dist: pytest; extra == "dev"
Requires-Dist: black; extra == "dev"
Requires-Dist: flake8; extra == "dev"
Dynamic: license-file
